pacman/__init__.py
pacman/__main__.py
pacman/cli.py
pacman/core/__init__.py
pacman/core/categorizer.py
pacman/core/models.py
pacman/core/privacy.py
pacman/dashboard/__init__.py
pacman/dashboard/app.py
pacman/importers/__init__.py
pacman/importers/base.py
pacman/importers/deutsche_bank.py
pacman/importers/dkb.py
pacman/importers/generic_csv.py
pacman/importers/ing.py
pacman/importers/n26.py
pacman/importers/sparkasse.py
pacman/jurisdictions/__init__.py
pacman/jurisdictions/base.py
pacman/jurisdictions/germany/__init__.py
pacman/jurisdictions/germany/constants.py
pacman/jurisdictions/germany/plugin.py
pacman/jurisdictions/germany/profiles/__init__.py
pacman/jurisdictions/germany/rules/__init__.py
pacman/jurisdictions/germany/rules/berater_coach.yaml
pacman/jurisdictions/germany/rules/content_creator.yaml
pacman/jurisdictions/germany/rules/e_commerce.yaml
pacman/jurisdictions/germany/rules/einzelunternehmer.yaml
pacman/jurisdictions/germany/rules/freiberufler.yaml
pacman/jurisdictions/germany/rules/gmbh_geschaeftsfuehrer.yaml
pacman/jurisdictions/germany/rules/handwerker.yaml
pacman/jurisdictions/germany/rules/heilberufler.yaml
pacman/jurisdictions/germany/rules/it_freelancer.yaml
pacman/jurisdictions/germany/rules/kleinunternehmer.yaml
pacman/jurisdictions/germany/rules/kuenstler.yaml
pacman/jurisdictions/germany/rules/nebenberuflich.yaml
pacman/jurisdictions/germany/rules/vermieter.yaml
pacman/utils/__init__.py
pacman/utils/dates.py
pacman/utils/money.py
pacman_tax-0.2.0.dist-info/METADATA
pacman_tax-0.2.0.dist-info/WHEEL
pacman_tax-0.2.0.dist-info/entry_points.txt
pacman_tax-0.2.0.dist-info/licenses/LICENSE
pacman_tax-0.2.0.dist-info/RECORD
