Metadata-Version: 2.4
Name: pacman-tax
Version: 0.2.0
Summary: PACMAN - Privacy-first Automated Calculation & Management of Numbers. Local-first tax automation for freelancers and landlords.
Project-URL: Homepage, https://github.com/noiion/pacman-tax
Project-URL: Documentation, https://github.com/noiion/pacman-tax#readme
Project-URL: Repository, https://github.com/noiion/pacman-tax
Project-URL: Issues, https://github.com/noiion/pacman-tax/issues
Author-email: Manu <noiion828@gmail.com>
License-Expression: AGPL-3.0-or-later
License-File: LICENSE
Keywords: ELSTER,EÜR,Vermietung,accounting,freelancer,local-first,privacy,tax
Classifier: Development Status :: 3 - Alpha
Classifier: Environment :: Console
Classifier: Intended Audience :: End Users/Desktop
Classifier: License :: OSI Approved :: GNU Affero General Public License v3 or later (AGPLv3+)
Classifier: Operating System :: OS Independent
Classifier: Programming Language :: Python :: 3
Classifier: Programming Language :: Python :: 3.10
Classifier: Programming Language :: Python :: 3.11
Classifier: Programming Language :: Python :: 3.12
Classifier: Topic :: Office/Business :: Financial :: Accounting
Classifier: Typing :: Typed
Requires-Python: >=3.10
Requires-Dist: openpyxl>=3.1.0
Requires-Dist: pandas>=2.0.0
Requires-Dist: pydantic>=2.0.0
Requires-Dist: pyyaml>=6.0
Requires-Dist: rich>=13.0.0
Requires-Dist: typer>=0.9.0
Provides-Extra: all
Requires-Dist: cryptography>=41.0.0; extra == 'all'
Requires-Dist: hypothesis>=6.0.0; extra == 'all'
Requires-Dist: mypy>=1.0.0; extra == 'all'
Requires-Dist: plotly>=5.18.0; extra == 'all'
Requires-Dist: pytest-cov>=4.0.0; extra == 'all'
Requires-Dist: pytest>=7.0.0; extra == 'all'
Requires-Dist: ruff>=0.1.0; extra == 'all'
Requires-Dist: streamlit>=1.30.0; extra == 'all'
Provides-Extra: crypto
Requires-Dist: cryptography>=41.0.0; extra == 'crypto'
Provides-Extra: dashboard
Requires-Dist: plotly>=5.18.0; extra == 'dashboard'
Requires-Dist: streamlit>=1.30.0; extra == 'dashboard'
Provides-Extra: dev
Requires-Dist: hypothesis>=6.0.0; extra == 'dev'
Requires-Dist: mypy>=1.0.0; extra == 'dev'
Requires-Dist: pytest-cov>=4.0.0; extra == 'dev'
Requires-Dist: pytest>=7.0.0; extra == 'dev'
Requires-Dist: ruff>=0.1.0; extra == 'dev'
